{
  "pools": [
    {
      "rolls": {
        "min": 1,
        "max": 1
      },
      "entries": [
        {
          "type": "minecraft:item",
          "weight": 30,
          "name": "minecraft:cooked_beef",
          "functions": [
            {
              "function": "minecraft:set_count",
              "count": {
                "min": 0,
                "max": 3
              }
            }
          ]
        },
        {
          "type": "minecraft:item",
          "weight": 10,
          "name": "minecraft:golden_apple",
          "functions": [
            {
              "function": "minecraft:set_count",
              "count": {
                "min": 0,
                "max": 1
              }
            }
          ]
        },
        {
          "type": "minecraft:item",
          "weight": 60,
          "name": "minecraft:emerald",
          "functions": [
            {
              "function": "minecraft:set_count",
              "count": {
                "min": 1,
                "max": 10
              }
            }
          ]
        }
      ]
    }
  ]
}